README.md
setup.cfg
setup.py
dadata/__init__.py
dadata/base_client.py
dadata/exceptions.py
dadata/find_party.py
dadata/standartization.py
dadata_client.egg-info/PKG-INFO
dadata_client.egg-info/SOURCES.txt
dadata_client.egg-info/dependency_links.txt
dadata_client.egg-info/not-zip-safe
dadata_client.egg-info/requires.txt
dadata_client.egg-info/top_level.txt