Metadata-Version: 1.0
Name: dadata-client
Version: 0.1.0
Summary: Dadata.ru python client
Home-page: https://github.com/f213/dadata-client/
Author: Fedor Borshev
Author-email: f@f213.in
License: MIT
Platform: UNKNOWN
